setup_env/__init__.py
scipionn_toolkit-1.0.4.dist-info/LICENSE
scipionn_toolkit-1.0.4.dist-info/METADATA
scipionn_toolkit-1.0.4.dist-info/WHEEL
scipionn_toolkit-1.0.4.dist-info/top_level.txt
scipionn_toolkit-1.0.4.dist-info/RECORD
