Metadata-Version: 2.1
Name: scipionn-toolkit
Version: 1.0.4
Summary: Xmipp neural network utilities for flexibility
Home-page: UNKNOWN
Author: David Herreros
Author-email: dherreros@cnb.csic.es
License: UNKNOWN
Keywords: scipion continuous-heterogeneity imageprocessing xmipp
Platform: UNKNOWN
